pyGRNN/GRNN.py
pyGRNN/__init__.py
pyGRNN/base.py
pyGRNN/feature_selection.py
pyGRNN-0.1.2.dist-info/LICENSE
pyGRNN-0.1.2.dist-info/METADATA
pyGRNN-0.1.2.dist-info/WHEEL
pyGRNN-0.1.2.dist-info/top_level.txt
pyGRNN-0.1.2.dist-info/RECORD
